task_editor/__init__.py
task_editor/task_editor.glade
task_editor/task_editor.glade~
task_editor/task_editor.py
gtk_task_editor-0.0.0.dist-info/WHEEL
gtk_task_editor-0.0.0.dist-info/METADATA
gtk_task_editor-0.0.0.dist-info/RECORD
